{
  "version": "0.2",
  "ignorePaths": ["package.json", "cspell.json", "CHANGELOG.md"],
  "dictionaryDefinitions": [],
  "dictionaries": [],
  "words": [
    "apos",
    "autopictureinpicture",
    "autoplay",
    "autoplays",
    "behaviour",
    "bfcache",
    "builtins",
    "canfullscreen",
    "caniuse",
    "canplay",
    "canplaythrough",
    "chromecast",
    "contenteditable",
    "controlslist",
    "crossorigin",
    "csspart",
    "cssprop",
    "currenttime",
    "dasharray",
    "dashoffset",
    "datetime",
    "diffable",
    "discoverables",
    "disablepictureinpicture",
    "disableremoteplayback",
    "enterpictureinpicture",
    "eqls",
    "exportsparts",
    "esbuild",
    "focusring",
    "fscreen",
    "fullscreen",
    "furf",
    "globby",
    "hlsjs",
    "ignore",
    "indigo",
    "jsdelivr",
    "keyframes",
    "keyof",
    "kleur",
    "loadedmetadata",
    "loggable",
    "mihar",
    "miracast",
    "mouseleave",
    "mpegurl",
    "mpga",
    "nodownload",
    "nofullscreen",
    "noremoteplayback",
    "noscroll",
    "nums",
    "pairable",
    "playhead",
    "playsinline",
    "plyr",
    "pnpm",
    "pointerdown",
    "pointermove",
    "pointerup",
    "postbuild",
    "postlink",
    "preact",
    "prefetch",
    "prefetched",
    "preload",
    "previewable",
    "progressbar",
    "quickstart",
    "redispatch",
    "redispatches",
    "remuxed",
    "roadmap",
    "seekable",
    "seekableamount",
    "seeked",
    "seekingrequestthrottle",
    "shiki",
    "slotchange",
    "streamable",
    "subcomponent",
    "sveltejs",
    "svelteness",
    "tabindex",
    "tada",
    "tagname",
    "tailwindcss",
    "TLDR",
    "totalduration",
    "touchstart",
    "turborepo",
    "unmute",
    "unplugin",
    "unmuted",
    "unmuting",
    "unsub",
    "unsubscriber",
    "unsubscribers",
    "userdata",
    "valuemax",
    "valuemin",
    "valuenext",
    "valuenow",
    "valuetext",
    "vercel",
    "vidstack",
    "vime",
    "vite",
    "vitebook",
    "vitest",
    "vorbis",
    "weba",
    "wirekit",
    "webkitpresentationmodechanged",
    "wombo"
  ],
  "ignoreWords": [],
  "import": []
}
